{
   "configurations": [
      {
         "name": "x64-Release-Deb 19",
         "generator": "Visual Studio 16 2019 Win64",
         "configurationType": "RelWithDebInfo",
         "inheritEnvironments": [ "msvc_x64" ],
         "buildRoot": "${workspaceRoot}\\cmake_build\\vs2019",
         "installRoot": "${workspaceRoot}\\cmake_build\\vs2019\\install",
         "cmakeCommandArgs": "-Wno-dev",
         "buildCommandArgs": "",
         "ctestCommandArgs": ""
      },
      {
         "name": "x64-Release 19",
         "generator": "Visual Studio 16 2019 Win64",
         "configurationType": "Release",
         "inheritEnvironments": [ "msvc_x64" ],
         "buildRoot": "${workspaceRoot}\\cmake_build\\vs2019",
         "installRoot": "${workspaceRoot}\\cmake_build\\vs2019\\install",
         "cmakeCommandArgs": "-Wno-dev",
         "buildCommandArgs": "",
         "ctestCommandArgs": ""
      },
      {
         "name": "x64-Debug 19",
         "generator": "Visual Studio 16 2019 Win64",
         "configurationType": "Debug",
         "inheritEnvironments": [ "msvc_x64" ],
         "buildRoot": "${workspaceRoot}\\cmake_build\\vs2019",
         "installRoot": "${workspaceRoot}\\cmake_build\\vs2019\\install",
         "cmakeCommandArgs": "-Wno-dev",
         "buildCommandArgs": "",
         "ctestCommandArgs": ""
      }
   ]
}